CHANGELOG.md
LICENSE
MANIFEST.in
README.rst
pytest.ini
setup.cfg
setup.py
config/app.example.cfg
config/auth.example.cfg
config/db.example.cfg
docs/Makefile
docs/conf.py
docs/credits.rst
docs/index.rst
docs/intro.rst
docs/make.bat
docs/requirements.txt
docs/testing.rst
docs/_static/repocribro-icon.png
docs/api/index.rst
docs/api/repocribro/api.rst
docs/api/repocribro/commands.rst
docs/api/repocribro/controllers.rst
docs/api/repocribro/ext_core.rst
docs/api/repocribro/extending.rst
docs/api/repocribro/manage.rst
docs/api/repocribro/models.rst
docs/api/repocribro/repocribro.rst
docs/api/repocribro/security.rst
docs/extensions/hooks.csv
docs/extensions/hooks.rst
docs/extensions/index.rst
docs/install/config.rst
docs/install/database.rst
docs/install/index.rst
docs/install/install.rst
docs/install/requirements.rst
docs/usage/commands.rst
docs/usage/index.rst
docs/usage/start.rst
docs/usage/web.rst
repocribro/__init__.py
repocribro/__main__.py
repocribro/api.py
repocribro/app.py
repocribro/database.py
repocribro/ext_core.py
repocribro/github.py
repocribro/manage.py
repocribro/models.py
repocribro/repocribro.py
repocribro/security.py
repocribro.egg-info/PKG-INFO
repocribro.egg-info/SOURCES.txt
repocribro.egg-info/dependency_links.txt
repocribro.egg-info/entry_points.txt
repocribro.egg-info/not-zip-safe
repocribro.egg-info/requires.txt
repocribro.egg-info/top_level.txt
repocribro/commands/__init__.py
repocribro/commands/assign_role.py
repocribro/commands/db_create.py
repocribro/commands/repocheck.py
repocribro/controllers/__init__.py
repocribro/controllers/admin.py
repocribro/controllers/auth.py
repocribro/controllers/core.py
repocribro/controllers/errors.py
repocribro/controllers/manage.py
repocribro/controllers/webhooks.py
repocribro/extending/__init__.py
repocribro/extending/extension.py
repocribro/extending/extension_master.py
repocribro/extending/helpers/__init__.py
repocribro/extending/helpers/views.py
repocribro/filters/__init__.py
repocribro/filters/common.py
repocribro/filters/models.py
repocribro/static/bootstrap.min.css
repocribro/static/bootstrap.min.js
repocribro/static/jquery.min.js
repocribro/static/pics
repocribro/static/script.js
repocribro/static/style.css
